{"id":"1","isOnline":true,"isPdf":false,"contestId":"fibonacci-secondarie-2023-seconda-fase-demo","schema":{"1":{"originalId":"3","pointsCorrect":5,"pointsBlank":1,"pointsWrong":0,"type":"multipleChoice","options":[{"id":"A","originalId":"D","correct":false},{"id":"B","originalId":"C","correct":false},{"id":"C","originalId":"A","correct":true},{"id":"D","originalId":"E","correct":false},{"id":"E","originalId":"B","correct":false}]},"2":{"originalId":"1","pointsCorrect":5,"pointsBlank":1,"pointsWrong":0,"type":"multipleChoice","options":[{"id":"A","originalId":"A","correct":true},{"id":"B","originalId":"C","correct":false},{"id":"C","originalId":"E","correct":false},{"id":"D","originalId":"D","correct":false},{"id":"E","originalId":"B","correct":false}]},"3":{"originalId":"2","pointsCorrect":5,"pointsBlank":1,"pointsWrong":0,"type":"multipleChoice","options":[{"id":"A","originalId":"E","correct":false},{"id":"B","originalId":"A","correct":true},{"id":"C","originalId":"B","correct":false},{"id":"D","originalId":"C","correct":false},{"id":"E","originalId":"D","correct":false}]},"4":{"originalId":"5","pointsCorrect":5,"pointsBlank":0,"pointsWrong":0,"type":"blockly","numTestcases":3},"5":{"originalId":"6","pointsCorrect":5,"pointsBlank":0,"pointsWrong":0,"type":"blockly","numTestcases":3},"6":{"originalId":"4","pointsCorrect":5,"pointsBlank":0,"pointsWrong":0,"type":"blockly","numTestcases":3}}}